turbo_quart/__init__.py
turbo_quart/turbo.py
Turbo_Quart-0.0.3.dist-info/LICENSE
Turbo_Quart-0.0.3.dist-info/METADATA
Turbo_Quart-0.0.3.dist-info/WHEEL
Turbo_Quart-0.0.3.dist-info/top_level.txt
Turbo_Quart-0.0.3.dist-info/RECORD
