Metadata-Version: 2.1
Name: Turbo-Quart
Version: 0.0.3
Summary: Use Hotwire Turbo in your Quart application.
Author-email: Ahmet Elgün <ahmetelgn@gmail.com>, Miguel Grinberg <miguel.grinberg@gmail.com>
Project-URL: Homepage, https://github.com/ahmetelgun/turbo-quart
Project-URL: Bug Tracker, https://github.com/ahmetelgun/turbo-quart/issues
Classifier: Environment :: Web Environment
Classifier: Intended Audience :: Developers
Classifier: Programming Language :: Python :: 3
Classifier: License :: OSI Approved :: MIT License
Classifier: Operating System :: OS Independent
Requires-Python: >=3.6
License-File: LICENSE
Requires-Dist: Quart >=0.19.4
